test_cookiecutter/__init__.py
test_cookiecutter/cli.py
test_cookiecutter/test_cookiecutter.py
test_cookiecutter-0.1.1.dist-info/DESCRIPTION.rst
test_cookiecutter-0.1.1.dist-info/METADATA
test_cookiecutter-0.1.1.dist-info/RECORD
test_cookiecutter-0.1.1.dist-info/WHEEL
test_cookiecutter-0.1.1.dist-info/entry_points.txt
test_cookiecutter-0.1.1.dist-info/metadata.json
test_cookiecutter-0.1.1.dist-info/top_level.txt
