Metadata-Version: 2.0
Name: test-cookiecutter
Version: 0.1.1
Summary: Python Boilerplate contains all the boilerplate you need to create a Python package.
Home-page: https://github.com/ibgp2/test_cookiecutter
Author: Marc-Olivier Buob
Author-email: marc-olivier.buob@nokia-bell-labs.com
License: GNU General Public License v3
Keywords: test_cookiecutter
Platform: UNKNOWN
Classifier: Development Status :: 2 - Pre-Alpha
Classifier: Intended Audience :: Developers
Classifier: License :: OSI Approved :: GNU General Public License v3 (GPLv3)
Classifier: Natural Language :: English
Classifier: Programming Language :: Python :: 3
Classifier: Programming Language :: Python :: 3.4
Classifier: Programming Language :: Python :: 3.5
Classifier: Programming Language :: Python :: 3.6
Requires-Dist: Click (>=6.0)
